{
  "meta": {
    "schemecode": "46627",
    "amfiSchemeCode": 150948,
    "isin": "INF174KA1ZD3",
    "fundName": "Kotak Silver ETF",
    "amfiSchemeName": "Kotak Silver ETF",
    "amfiAmcName": "Kotak Mahindra Mutual Fund",
    "classification": "Metal : ETFs",
    "plan": "unknown",
    "option": "unknown",
    "isEtf": true,
    "isFof": false,
    "firstDate": "2025-02-28",
    "lastDate": "2026-05-29",
    "points": 307,
    "stage": 1,
    "ruleVersion": 1,
    "parserVersion": 1,
    "generatedAt": "2026-05-31T04:11:17.368Z",
    "lastForwardAppendAt": null,
    "provenance": {
      "backfillSource": "AMFI DownloadNAVHistoryReport_Po.aspx",
      "backfillWindows": [
        {
          "from": "28-Feb-2025",
          "to": "07-Mar-2025",
          "fetchedAt": "2026-05-31T04:11:17.375Z"
        },
        {
          "from": "08-Mar-2025",
          "to": "21-May-2025",
          "fetchedAt": "2026-05-31T04:11:22.239Z"
        },
        {
          "from": "22-May-2025",
          "to": "04-Aug-2025",
          "fetchedAt": "2026-05-31T04:11:33.487Z"
        },
        {
          "from": "05-Aug-2025",
          "to": "18-Oct-2025",
          "fetchedAt": "2026-05-31T04:11:45.736Z"
        },
        {
          "from": "19-Oct-2025",
          "to": "01-Jan-2026",
          "fetchedAt": "2026-05-31T04:11:57.786Z"
        },
        {
          "from": "02-Jan-2026",
          "to": "17-Mar-2026",
          "fetchedAt": "2026-05-31T04:12:11.289Z"
        },
        {
          "from": "18-Mar-2026",
          "to": "31-May-2026",
          "fetchedAt": "2026-05-31T04:12:24.229Z"
        }
      ],
      "forwardSource": "AMFI NAVAll.txt (via scripts/ingest/nav-latest.ts) — to be wired in a later phase",
      "parser": "scripts/ingest/nav-history-backfill.ts:parseHistoricalInto",
      "parserVersion": 1
    }
  },
  "series": [
    [
      "2025-02-28",
      91.8302
    ],
    [
      "2025-03-03",
      92.5371
    ],
    [
      "2025-03-04",
      93.6139
    ],
    [
      "2025-03-05",
      94.5086
    ],
    [
      "2025-03-06",
      94.7519
    ],
    [
      "2025-03-07",
      95.0105
    ],
    [
      "2025-03-10",
      95.0126
    ],
    [
      "2025-03-11",
      94.9186
    ],
    [
      "2025-03-12",
      96.0325
    ],
    [
      "2025-03-13",
      96.3129
    ],
    [
      "2025-03-17",
      97.7692
    ],
    [
      "2025-03-18",
      98.4195
    ],
    [
      "2025-03-19",
      97.8569
    ],
    [
      "2025-03-20",
      96.3001
    ],
    [
      "2025-03-21",
      95.5533
    ],
    [
      "2025-03-24",
      95.5611
    ],
    [
      "2025-03-25",
      95.8454
    ],
    [
      "2025-03-26",
      97.0166
    ],
    [
      "2025-03-27",
      97.7377
    ],
    [
      "2025-03-28",
      98.8936
    ],
    [
      "2025-03-31",
      98.1691
    ],
    [
      "2025-04-01",
      97.8005
    ],
    [
      "2025-04-02",
      97.7658
    ],
    [
      "2025-04-03",
      94.0417
    ],
    [
      "2025-04-04",
      90.943
    ],
    [
      "2025-04-07",
      88.5727
    ],
    [
      "2025-04-08",
      88.4884
    ],
    [
      "2025-04-09",
      88.9499
    ],
    [
      "2025-04-11",
      91.465
    ],
    [
      "2025-04-15",
      93.459
    ],
    [
      "2025-04-16",
      94.7497
    ],
    [
      "2025-04-17",
      93.2518
    ],
    [
      "2025-04-21",
      94.3563
    ],
    [
      "2025-04-22",
      93.856
    ],
    [
      "2025-04-23",
      94.6268
    ],
    [
      "2025-04-24",
      95.7378
    ],
    [
      "2025-04-25",
      95.7442
    ],
    [
      "2025-04-28",
      94.3675
    ],
    [
      "2025-04-29",
      95.6707
    ],
    [
      "2025-04-30",
      92.4187
    ],
    [
      "2025-05-02",
      92.5898
    ],
    [
      "2025-05-05",
      92.4052
    ],
    [
      "2025-05-06",
      93.9973
    ],
    [
      "2025-05-07",
      93.8583
    ],
    [
      "2025-05-08",
      93.7192
    ],
    [
      "2025-05-09",
      93.964
    ],
    [
      "2025-05-12",
      92.226
    ],
    [
      "2025-05-13",
      95.0939
    ],
    [
      "2025-05-14",
      94.4281
    ],
    [
      "2025-05-15",
      92.7948
    ],
    [
      "2025-05-16",
      93.1519
    ],
    [
      "2025-05-19",
      93.7887
    ],
    [
      "2025-05-20",
      93.7369
    ],
    [
      "2025-05-21",
      95.5842
    ],
    [
      "2025-05-22",
      95.7946
    ],
    [
      "2025-05-23",
      95.149
    ],
    [
      "2025-05-26",
      95.4374
    ],
    [
      "2025-05-27",
      94.9586
    ],
    [
      "2025-05-28",
      95.9465
    ],
    [
      "2025-05-29",
      96.0228
    ],
    [
      "2025-05-30",
      95.5208
    ],
    [
      "2025-06-02",
      95.6898
    ],
    [
      "2025-06-03",
      98.2952
    ],
    [
      "2025-06-04",
      99.2336
    ],
    [
      "2025-06-05",
      101.953
    ],
    [
      "2025-06-06",
      102.918
    ],
    [
      "2025-06-09",
      103.4205
    ],
    [
      "2025-06-10",
      104.2206
    ],
    [
      "2025-06-11",
      103.4057
    ],
    [
      "2025-06-12",
      102.9077
    ],
    [
      "2025-06-13",
      103.7901
    ],
    [
      "2025-06-16",
      104.1835
    ],
    [
      "2025-06-17",
      106.0557
    ],
    [
      "2025-06-18",
      106.9052
    ],
    [
      "2025-06-19",
      105.0492
    ],
    [
      "2025-06-20",
      104.3238
    ],
    [
      "2025-06-23",
      104.6558
    ],
    [
      "2025-06-24",
      103.8584
    ],
    [
      "2025-06-25",
      103.0075
    ],
    [
      "2025-06-26",
      104.8597
    ],
    [
      "2025-06-27",
      102.7279
    ],
    [
      "2025-06-30",
      103.5858
    ],
    [
      "2025-07-01",
      104.4489
    ],
    [
      "2025-07-02",
      103.8575
    ],
    [
      "2025-07-03",
      105.1308
    ],
    [
      "2025-07-04",
      105.0685
    ],
    [
      "2025-07-07",
      104.8656
    ],
    [
      "2025-07-08",
      105.1637
    ],
    [
      "2025-07-09",
      104.8361
    ],
    [
      "2025-07-10",
      104.9945
    ],
    [
      "2025-07-11",
      107.9054
    ],
    [
      "2025-07-14",
      111.2811
    ],
    [
      "2025-07-15",
      109.3915
    ],
    [
      "2025-07-16",
      108.9109
    ],
    [
      "2025-07-17",
      108.4621
    ],
    [
      "2025-07-18",
      110.1547
    ],
    [
      "2025-07-21",
      110.7932
    ],
    [
      "2025-07-22",
      111.6677
    ],
    [
      "2025-07-23",
      113.1995
    ],
    [
      "2025-07-24",
      112.2652
    ],
    [
      "2025-07-25",
      111.7809
    ],
    [
      "2025-07-28",
      110.3551
    ],
    [
      "2025-07-29",
      110.7161
    ],
    [
      "2025-07-30",
      110.8928
    ],
    [
      "2025-07-31",
      107.6413
    ],
    [
      "2025-08-01",
      107.0772
    ],
    [
      "2025-08-04",
      109.0689
    ],
    [
      "2025-08-05",
      109.6373
    ],
    [
      "2025-08-06",
      110.7016
    ],
    [
      "2025-08-07",
      112.4919
    ],
    [
      "2025-08-08",
      112.1618
    ],
    [
      "2025-08-11",
      111.0462
    ],
    [
      "2025-08-12",
      110.6721
    ],
    [
      "2025-08-13",
      112.5068
    ],
    [
      "2025-08-14",
      112.2142
    ],
    [
      "2025-08-18",
      111.4298
    ],
    [
      "2025-08-19",
      110.8829
    ],
    [
      "2025-08-20",
      108.3691
    ],
    [
      "2025-08-21",
      110.2125
    ],
    [
      "2025-08-22",
      111.1762
    ],
    [
      "2025-08-25",
      113.417
    ],
    [
      "2025-08-26",
      113.0698
    ],
    [
      "2025-08-28",
      114.196
    ],
    [
      "2025-08-29",
      114.7324
    ],
    [
      "2025-09-01",
      119.8371
    ],
    [
      "2025-09-02",
      119.7712
    ],
    [
      "2025-09-03",
      119.8519
    ],
    [
      "2025-09-04",
      120.327
    ],
    [
      "2025-09-05",
      120.2327
    ],
    [
      "2025-09-08",
      121.2424
    ],
    [
      "2025-09-09",
      121.5754
    ],
    [
      "2025-09-10",
      121.3468
    ],
    [
      "2025-09-11",
      121.2518
    ],
    [
      "2025-09-12",
      124.793
    ],
    [
      "2025-09-15",
      124.3599
    ],
    [
      "2025-09-16",
      125.6623
    ],
    [
      "2025-09-17",
      122.3065
    ],
    [
      "2025-09-18",
      123.7413
    ],
    [
      "2025-09-19",
      124.7158
    ],
    [
      "2025-09-22",
      129.2258
    ],
    [
      "2025-09-23",
      131.3848
    ],
    [
      "2025-09-24",
      130.6723
    ],
    [
      "2025-09-25",
      133.587
    ],
    [
      "2025-09-26",
      134.373
    ],
    [
      "2025-09-29",
      139.9153
    ],
    [
      "2025-09-30",
      138.0257
    ],
    [
      "2025-10-01",
      140.8546
    ],
    [
      "2025-10-03",
      141.0642
    ],
    [
      "2025-10-06",
      144.6298
    ],
    [
      "2025-10-07",
      145.0322
    ],
    [
      "2025-10-08",
      148.4141
    ],
    [
      "2025-10-09",
      153.4735
    ],
    [
      "2025-10-10",
      157.5931
    ],
    [
      "2025-10-13",
      165.6657
    ],
    [
      "2025-10-14",
      172.2408
    ],
    [
      "2025-10-15",
      169.678
    ],
    [
      "2025-10-16",
      163.9446
    ],
    [
      "2025-10-17",
      165.4695
    ],
    [
      "2025-10-20",
      153.9618
    ],
    [
      "2025-10-23",
      146.9453
    ],
    [
      "2025-10-24",
      143.6057
    ],
    [
      "2025-10-27",
      141.8457
    ],
    [
      "2025-10-28",
      138.0419
    ],
    [
      "2025-10-29",
      142.8088
    ],
    [
      "2025-10-30",
      142.188
    ],
    [
      "2025-10-31",
      144.4307
    ],
    [
      "2025-11-03",
      144.4427
    ],
    [
      "2025-11-04",
      141.6921
    ],
    [
      "2025-11-06",
      143.5297
    ],
    [
      "2025-11-07",
      144.0821
    ],
    [
      "2025-11-10",
      147.0223
    ],
    [
      "2025-11-11",
      149.5712
    ],
    [
      "2025-11-12",
      151.7633
    ],
    [
      "2025-11-13",
      158.7307
    ],
    [
      "2025-11-14",
      155.1241
    ],
    [
      "2025-11-17",
      150.8002
    ],
    [
      "2025-11-18",
      148.9457
    ],
    [
      "2025-11-19",
      153.3238
    ],
    [
      "2025-11-20",
      150.1152
    ],
    [
      "2025-11-21",
      146.5131
    ],
    [
      "2025-11-24",
      148.7068
    ],
    [
      "2025-11-25",
      151.2965
    ],
    [
      "2025-11-26",
      153.9625
    ],
    [
      "2025-11-27",
      157.3171
    ],
    [
      "2025-11-28",
      159.0141
    ],
    [
      "2025-12-01",
      169.7709
    ],
    [
      "2025-12-02",
      168.6762
    ],
    [
      "2025-12-03",
      172.2996
    ],
    [
      "2025-12-04",
      169.9623
    ],
    [
      "2025-12-05",
      172.5136
    ],
    [
      "2025-12-08",
      173.0884
    ],
    [
      "2025-12-09",
      173.1005
    ],
    [
      "2025-12-10",
      179.0121
    ],
    [
      "2025-12-11",
      182.17
    ],
    [
      "2025-12-12",
      187.3755
    ],
    [
      "2025-12-15",
      186.7557
    ],
    [
      "2025-12-16",
      185.8751
    ],
    [
      "2025-12-17",
      193.1085
    ],
    [
      "2025-12-18",
      193.5274
    ],
    [
      "2025-12-19",
      193.3698
    ],
    [
      "2025-12-22",
      200.9144
    ],
    [
      "2025-12-23",
      202.9748
    ],
    [
      "2025-12-24",
      211.3452
    ],
    [
      "2025-12-26",
      220.7971
    ],
    [
      "2025-12-29",
      224.9725
    ],
    [
      "2025-12-30",
      222.9535
    ],
    [
      "2025-12-31",
      221.2927
    ],
    [
      "2026-01-01",
      219.777
    ],
    [
      "2026-01-02",
      224.4169
    ],
    [
      "2026-01-05",
      229.7067
    ],
    [
      "2026-01-06",
      233.1293
    ],
    [
      "2026-01-07",
      237.3452
    ],
    [
      "2026-01-08",
      227.1907
    ],
    [
      "2026-01-09",
      233.4267
    ],
    [
      "2026-01-12",
      246.9423
    ],
    [
      "2026-01-13",
      252.3958
    ],
    [
      "2026-01-14",
      268.3981
    ],
    [
      "2026-01-16",
      272.7567
    ],
    [
      "2026-01-19",
      280.9534
    ],
    [
      "2026-01-20",
      295.8979
    ],
    [
      "2026-01-21",
      302.9046
    ],
    [
      "2026-01-22",
      283.6501
    ],
    [
      "2026-01-23",
      304.0226
    ],
    [
      "2026-01-27",
      331.6086
    ],
    [
      "2026-01-28",
      344.9497
    ],
    [
      "2026-01-29",
      364.5629
    ],
    [
      "2026-01-30",
      320.1483
    ],
    [
      "2026-02-01",
      320.1411
    ],
    [
      "2026-02-02",
      241.0285
    ],
    [
      "2026-02-03",
      254.9122
    ],
    [
      "2026-02-04",
      271.6331
    ],
    [
      "2026-02-05",
      241.8414
    ],
    [
      "2026-02-06",
      232.5108
    ],
    [
      "2026-02-09",
      243.3808
    ],
    [
      "2026-02-10",
      249.5006
    ],
    [
      "2026-02-11",
      253.1567
    ],
    [
      "2026-02-12",
      250.0148
    ],
    [
      "2026-02-13",
      236.9196
    ],
    [
      "2026-02-16",
      232.4172
    ],
    [
      "2026-02-17",
      225.4655
    ],
    [
      "2026-02-18",
      228.3205
    ],
    [
      "2026-02-19",
      235.5877
    ],
    [
      "2026-02-20",
      240.7795
    ],
    [
      "2026-02-23",
      255.1097
    ],
    [
      "2026-02-24",
      255.2562
    ],
    [
      "2026-02-25",
      256.5833
    ],
    [
      "2026-02-26",
      250.5571
    ],
    [
      "2026-02-27",
      25.6016
    ],
    [
      "2026-03-02",
      27.8521
    ],
    [
      "2026-03-04",
      26.8643
    ],
    [
      "2026-03-05",
      25.2643
    ],
    [
      "2026-03-06",
      25.0981
    ],
    [
      "2026-03-09",
      25.1271
    ],
    [
      "2026-03-10",
      25.9743
    ],
    [
      "2026-03-11",
      25.5918
    ],
    [
      "2026-03-12",
      25.8341
    ],
    [
      "2026-03-13",
      25.0432
    ],
    [
      "2026-03-16",
      23.5613
    ],
    [
      "2026-03-17",
      24.2803
    ],
    [
      "2026-03-18",
      23.9752
    ],
    [
      "2026-03-19",
      22.1621
    ],
    [
      "2026-03-20",
      22.2045
    ],
    [
      "2026-03-23",
      20.2171
    ],
    [
      "2026-03-24",
      21.6225
    ],
    [
      "2026-03-25",
      22.5532
    ],
    [
      "2026-03-27",
      21.3601
    ],
    [
      "2026-03-30",
      22.0412
    ],
    [
      "2026-03-31",
      22.5696
    ],
    [
      "2026-04-01",
      23.0479
    ],
    [
      "2026-04-02",
      21.9235
    ],
    [
      "2026-04-06",
      22.5189
    ],
    [
      "2026-04-07",
      22.2229
    ],
    [
      "2026-04-08",
      23.3869
    ],
    [
      "2026-04-09",
      22.7206
    ],
    [
      "2026-04-10",
      23.0797
    ],
    [
      "2026-04-13",
      22.7975
    ],
    [
      "2026-04-15",
      23.9239
    ],
    [
      "2026-04-16",
      24.1212
    ],
    [
      "2026-04-17",
      24.0544
    ],
    [
      "2026-04-20",
      24.0931
    ],
    [
      "2026-04-21",
      24.1117
    ],
    [
      "2026-04-22",
      23.8969
    ],
    [
      "2026-04-23",
      23.1152
    ],
    [
      "2026-04-24",
      23.1923
    ],
    [
      "2026-04-27",
      23.4632
    ],
    [
      "2026-04-28",
      22.8614
    ],
    [
      "2026-04-29",
      22.7571
    ],
    [
      "2026-04-30",
      23.081
    ],
    [
      "2026-05-04",
      23.082
    ],
    [
      "2026-05-05",
      23.1357
    ],
    [
      "2026-05-06",
      23.9808
    ],
    [
      "2026-05-07",
      24.5215
    ],
    [
      "2026-05-08",
      24.5694
    ],
    [
      "2026-05-11",
      24.6164
    ],
    [
      "2026-05-12",
      25.458
    ],
    [
      "2026-05-13",
      27.6151
    ],
    [
      "2026-05-14",
      27.582
    ],
    [
      "2026-05-15",
      25.7749
    ],
    [
      "2026-05-18",
      25.7724
    ],
    [
      "2026-05-19",
      25.7938
    ],
    [
      "2026-05-20",
      25.7292
    ],
    [
      "2026-05-21",
      25.4567
    ],
    [
      "2026-05-22",
      25.5965
    ],
    [
      "2026-05-25",
      26.0276
    ],
    [
      "2026-05-26",
      25.6135
    ],
    [
      "2026-05-27",
      25.0849
    ],
    [
      "2026-05-29",
      25.3165
    ]
  ]
}
