{
  "meta": {
    "schemecode": "48114-D",
    "amfiSchemeCode": 151901,
    "isin": "INF179KC1GU0",
    "fundName": "HDFC Transportation and Logistics Fund-Reg(G)",
    "amfiSchemeName": "HDFC Transportation and Logistics Fund - Growth Option - Direct Plan",
    "amfiAmcName": "HDFC Mutual Fund",
    "classification": "Equity : Sectoral - Auto",
    "plan": "direct",
    "option": "growth",
    "isEtf": false,
    "isFof": false,
    "firstDate": "2023-08-17",
    "lastDate": "2026-07-06",
    "points": 707,
    "stage": 3,
    "ruleVersion": 1,
    "parserVersion": 2,
    "generatedAt": "2026-06-22T12:31:30.123Z",
    "lastForwardAppendAt": "2026-07-06T21:40:12.602Z",
    "provenance": {
      "backfillSource": "AMFI bulk CSV (mf-data/YYYY/MM/DD.csv)",
      "source": "mf-data",
      "parser": "scripts/ingest/nav-history-from-mfdata.ts",
      "parserVersion": 2,
      "forwardSource": "AMFI NAVAll.txt (nav-daily-refresh.ts)",
      "firstFile": "mf-data/2016/01/01.csv",
      "lastFile": "mf-data/2026/06/21.csv"
    }
  },
  "series": [
    [
      "2023-08-17",
      10.003
    ],
    [
      "2023-08-18",
      10.005
    ],
    [
      "2023-08-21",
      10.011
    ],
    [
      "2023-08-22",
      10.036
    ],
    [
      "2023-08-23",
      10.063
    ],
    [
      "2023-08-24",
      10.054
    ],
    [
      "2023-08-25",
      10.004
    ],
    [
      "2023-08-28",
      10.049
    ],
    [
      "2023-08-29",
      10.085
    ],
    [
      "2023-08-30",
      10.156
    ],
    [
      "2023-08-31",
      10.139
    ],
    [
      "2023-09-01",
      10.211
    ],
    [
      "2023-09-04",
      10.204
    ],
    [
      "2023-09-05",
      10.201
    ],
    [
      "2023-09-06",
      10.215
    ],
    [
      "2023-09-07",
      10.26
    ],
    [
      "2023-09-08",
      10.343
    ],
    [
      "2023-09-11",
      10.415
    ],
    [
      "2023-09-12",
      10.227
    ],
    [
      "2023-09-13",
      10.257
    ],
    [
      "2023-09-14",
      10.309
    ],
    [
      "2023-09-15",
      10.42
    ],
    [
      "2023-09-18",
      10.431
    ],
    [
      "2023-09-20",
      10.373
    ],
    [
      "2023-09-21",
      10.257
    ],
    [
      "2023-09-22",
      10.265
    ],
    [
      "2023-09-25",
      10.277
    ],
    [
      "2023-09-26",
      10.321
    ],
    [
      "2023-09-27",
      10.347
    ],
    [
      "2023-09-29",
      10.325
    ],
    [
      "2023-10-03",
      10.309
    ],
    [
      "2023-10-04",
      10.221
    ],
    [
      "2023-10-05",
      10.308
    ],
    [
      "2023-10-06",
      10.377
    ],
    [
      "2023-10-09",
      10.255
    ],
    [
      "2023-10-10",
      10.403
    ],
    [
      "2023-10-11",
      10.45
    ],
    [
      "2023-10-12",
      10.525
    ],
    [
      "2023-10-13",
      10.573
    ],
    [
      "2023-10-16",
      10.611
    ],
    [
      "2023-10-17",
      10.672
    ],
    [
      "2023-10-18",
      10.654
    ],
    [
      "2023-10-19",
      10.675
    ],
    [
      "2023-10-20",
      10.586
    ],
    [
      "2023-10-23",
      10.308
    ],
    [
      "2023-10-25",
      10.246
    ],
    [
      "2023-10-26",
      10.141
    ],
    [
      "2023-10-27",
      10.269
    ],
    [
      "2023-10-30",
      10.22
    ],
    [
      "2023-10-31",
      10.148
    ],
    [
      "2023-11-01",
      10.097
    ],
    [
      "2023-11-02",
      10.22
    ],
    [
      "2023-11-03",
      10.352
    ],
    [
      "2023-11-06",
      10.439
    ],
    [
      "2023-11-07",
      10.447
    ],
    [
      "2023-11-08",
      10.51
    ],
    [
      "2023-11-09",
      10.523
    ],
    [
      "2023-11-10",
      10.518
    ],
    [
      "2023-11-13",
      10.6
    ],
    [
      "2023-11-15",
      10.74
    ],
    [
      "2023-11-16",
      10.825
    ],
    [
      "2023-11-17",
      10.935
    ],
    [
      "2023-11-20",
      10.888
    ],
    [
      "2023-11-21",
      10.941
    ],
    [
      "2023-11-22",
      10.9
    ],
    [
      "2023-11-23",
      10.928
    ],
    [
      "2023-11-24",
      10.917
    ],
    [
      "2023-11-28",
      11.017
    ],
    [
      "2023-11-29",
      11.118
    ],
    [
      "2023-11-30",
      11.152
    ],
    [
      "2023-12-01",
      11.174
    ],
    [
      "2023-12-04",
      11.302
    ],
    [
      "2023-12-05",
      11.336
    ],
    [
      "2023-12-06",
      11.379
    ],
    [
      "2023-12-07",
      11.427
    ],
    [
      "2023-12-08",
      11.324
    ],
    [
      "2023-12-11",
      11.327
    ],
    [
      "2023-12-12",
      11.289
    ],
    [
      "2023-12-13",
      11.382
    ],
    [
      "2023-12-14",
      11.467
    ],
    [
      "2023-12-15",
      11.463
    ],
    [
      "2023-12-18",
      11.542
    ],
    [
      "2023-12-19",
      11.507
    ],
    [
      "2023-12-20",
      11.175
    ],
    [
      "2023-12-21",
      11.223
    ],
    [
      "2023-12-22",
      11.353
    ],
    [
      "2023-12-26",
      11.393
    ],
    [
      "2023-12-27",
      11.518
    ],
    [
      "2023-12-28",
      11.573
    ],
    [
      "2023-12-29",
      11.695
    ],
    [
      "2024-01-01",
      11.741
    ],
    [
      "2024-01-02",
      11.641
    ],
    [
      "2024-01-03",
      11.688
    ],
    [
      "2024-01-04",
      11.732
    ],
    [
      "2024-01-05",
      11.786
    ],
    [
      "2024-01-08",
      11.732
    ],
    [
      "2024-01-09",
      11.828
    ],
    [
      "2024-01-10",
      11.871
    ],
    [
      "2024-01-11",
      11.987
    ],
    [
      "2024-01-12",
      12.004
    ],
    [
      "2024-01-15",
      11.998
    ],
    [
      "2024-01-16",
      11.956
    ],
    [
      "2024-01-17",
      11.794
    ],
    [
      "2024-01-18",
      11.812
    ],
    [
      "2024-01-19",
      11.927
    ],
    [
      "2024-01-23",
      11.697
    ],
    [
      "2024-01-24",
      11.862
    ],
    [
      "2024-01-25",
      11.92
    ],
    [
      "2024-01-29",
      12.077
    ],
    [
      "2024-01-30",
      12.162
    ],
    [
      "2024-01-31",
      12.365
    ],
    [
      "2024-02-01",
      12.472
    ],
    [
      "2024-02-02",
      12.545
    ],
    [
      "2024-02-05",
      12.605
    ],
    [
      "2024-02-06",
      12.706
    ],
    [
      "2024-02-07",
      12.683
    ],
    [
      "2024-02-08",
      12.557
    ],
    [
      "2024-02-09",
      12.442
    ],
    [
      "2024-02-12",
      12.341
    ],
    [
      "2024-02-13",
      12.344
    ],
    [
      "2024-02-14",
      12.505
    ],
    [
      "2024-02-15",
      12.656
    ],
    [
      "2024-02-16",
      12.895
    ],
    [
      "2024-02-19",
      12.959
    ],
    [
      "2024-02-20",
      12.883
    ],
    [
      "2024-02-21",
      12.765
    ],
    [
      "2024-02-22",
      12.971
    ],
    [
      "2024-02-23",
      13.014
    ],
    [
      "2024-02-26",
      12.99
    ],
    [
      "2024-02-27",
      13.066
    ],
    [
      "2024-02-28",
      12.813
    ],
    [
      "2024-02-29",
      12.841
    ],
    [
      "2024-03-01",
      13.04
    ],
    [
      "2024-03-04",
      13.077
    ],
    [
      "2024-03-05",
      13.155
    ],
    [
      "2024-03-06",
      13.073
    ],
    [
      "2024-03-07",
      13.067
    ],
    [
      "2024-03-11",
      12.908
    ],
    [
      "2024-03-12",
      12.846
    ],
    [
      "2024-03-13",
      12.375
    ],
    [
      "2024-03-14",
      12.577
    ],
    [
      "2024-03-15",
      12.602
    ],
    [
      "2024-03-18",
      12.695
    ],
    [
      "2024-03-19",
      12.625
    ],
    [
      "2024-03-20",
      12.719
    ],
    [
      "2024-03-21",
      12.932
    ],
    [
      "2024-03-22",
      13.131
    ],
    [
      "2024-03-26",
      13.217
    ],
    [
      "2024-03-27",
      13.274
    ],
    [
      "2024-03-28",
      13.38
    ],
    [
      "2024-03-31",
      13.379
    ],
    [
      "2024-04-01",
      13.489
    ],
    [
      "2024-04-02",
      13.622
    ],
    [
      "2024-04-03",
      13.626
    ],
    [
      "2024-04-04",
      13.698
    ],
    [
      "2024-04-05",
      13.706
    ],
    [
      "2024-04-08",
      13.838
    ],
    [
      "2024-04-09",
      13.827
    ],
    [
      "2024-04-10",
      13.853
    ],
    [
      "2024-04-12",
      13.784
    ],
    [
      "2024-04-15",
      13.624
    ],
    [
      "2024-04-16",
      13.659
    ],
    [
      "2024-04-18",
      13.601
    ],
    [
      "2024-04-19",
      13.657
    ],
    [
      "2024-04-22",
      13.765
    ],
    [
      "2024-04-23",
      13.848
    ],
    [
      "2024-04-24",
      13.838
    ],
    [
      "2024-04-25",
      13.945
    ],
    [
      "2024-04-26",
      13.967
    ],
    [
      "2024-04-29",
      14.018
    ],
    [
      "2024-04-30",
      14.216
    ],
    [
      "2024-05-02",
      14.396
    ],
    [
      "2024-05-03",
      14.319
    ],
    [
      "2024-05-06",
      14.295
    ],
    [
      "2024-05-07",
      14.066
    ],
    [
      "2024-05-08",
      14.202
    ],
    [
      "2024-05-09",
      14.18
    ],
    [
      "2024-05-10",
      14.316
    ],
    [
      "2024-05-13",
      14.212
    ],
    [
      "2024-05-14",
      14.386
    ],
    [
      "2024-05-15",
      14.443
    ],
    [
      "2024-05-16",
      14.594
    ],
    [
      "2024-05-17",
      14.809
    ],
    [
      "2024-05-21",
      14.802
    ],
    [
      "2024-05-22",
      14.9
    ],
    [
      "2024-05-23",
      15.095
    ],
    [
      "2024-05-24",
      15.1
    ],
    [
      "2024-05-27",
      15.029
    ],
    [
      "2024-05-28",
      14.95
    ],
    [
      "2024-05-29",
      14.885
    ],
    [
      "2024-05-30",
      14.755
    ],
    [
      "2024-05-31",
      14.73
    ],
    [
      "2024-06-03",
      15.012
    ],
    [
      "2024-06-04",
      14.354
    ],
    [
      "2024-06-05",
      14.94
    ],
    [
      "2024-06-06",
      15.101
    ],
    [
      "2024-06-07",
      15.342
    ],
    [
      "2024-06-10",
      15.405
    ],
    [
      "2024-06-11",
      15.564
    ],
    [
      "2024-06-12",
      15.607
    ],
    [
      "2024-06-13",
      15.756
    ],
    [
      "2024-06-14",
      15.989
    ],
    [
      "2024-06-18",
      16.233
    ],
    [
      "2024-06-19",
      16.084
    ],
    [
      "2024-06-20",
      16.002
    ],
    [
      "2024-06-21",
      15.939
    ],
    [
      "2024-06-24",
      16.017
    ],
    [
      "2024-06-25",
      16.045
    ],
    [
      "2024-06-26",
      15.982
    ],
    [
      "2024-06-27",
      16.047
    ],
    [
      "2024-06-28",
      16.056
    ],
    [
      "2024-07-01",
      16.179
    ],
    [
      "2024-07-02",
      16.152
    ],
    [
      "2024-07-03",
      16.21
    ],
    [
      "2024-07-04",
      16.306
    ],
    [
      "2024-07-05",
      16.357
    ],
    [
      "2024-07-08",
      16.261
    ],
    [
      "2024-07-09",
      16.523
    ],
    [
      "2024-07-10",
      16.308
    ],
    [
      "2024-07-11",
      16.3
    ],
    [
      "2024-07-12",
      16.237
    ],
    [
      "2024-07-15",
      16.337
    ],
    [
      "2024-07-16",
      16.373
    ],
    [
      "2024-07-18",
      16.381
    ],
    [
      "2024-07-19",
      16.017
    ],
    [
      "2024-07-22",
      16.109
    ],
    [
      "2024-07-23",
      16.127
    ],
    [
      "2024-07-24",
      16.253
    ],
    [
      "2024-07-25",
      16.329
    ],
    [
      "2024-07-26",
      16.606
    ],
    [
      "2024-07-29",
      16.652
    ],
    [
      "2024-07-30",
      16.747
    ],
    [
      "2024-07-31",
      16.796
    ],
    [
      "2024-08-01",
      16.738
    ],
    [
      "2024-08-02",
      16.484
    ],
    [
      "2024-08-05",
      15.916
    ],
    [
      "2024-08-06",
      15.839
    ],
    [
      "2024-08-07",
      16.07
    ],
    [
      "2024-08-08",
      15.973
    ],
    [
      "2024-08-09",
      16.225
    ],
    [
      "2024-08-12",
      16.291
    ],
    [
      "2024-08-13",
      16.122
    ],
    [
      "2024-08-14",
      16.087
    ],
    [
      "2024-08-16",
      16.55
    ],
    [
      "2024-08-19",
      16.532
    ],
    [
      "2024-08-20",
      16.584
    ],
    [
      "2024-08-21",
      16.668
    ],
    [
      "2024-08-22",
      16.686
    ],
    [
      "2024-08-23",
      16.775
    ],
    [
      "2024-08-26",
      16.766
    ],
    [
      "2024-08-27",
      16.75
    ],
    [
      "2024-08-28",
      16.699
    ],
    [
      "2024-08-29",
      16.659
    ],
    [
      "2024-08-30",
      16.75
    ],
    [
      "2024-09-02",
      16.657
    ],
    [
      "2024-09-03",
      16.672
    ],
    [
      "2024-09-04",
      16.602
    ],
    [
      "2024-09-05",
      16.678
    ],
    [
      "2024-09-06",
      16.474
    ],
    [
      "2024-09-09",
      16.508
    ],
    [
      "2024-09-10",
      16.651
    ],
    [
      "2024-09-11",
      16.572
    ],
    [
      "2024-09-12",
      16.846
    ],
    [
      "2024-09-13",
      16.818
    ],
    [
      "2024-09-16",
      16.786
    ],
    [
      "2024-09-17",
      16.86
    ],
    [
      "2024-09-18",
      16.816
    ],
    [
      "2024-09-19",
      16.832
    ],
    [
      "2024-09-20",
      17.111
    ],
    [
      "2024-09-23",
      17.245
    ],
    [
      "2024-09-24",
      17.267
    ],
    [
      "2024-09-25",
      17.18
    ],
    [
      "2024-09-26",
      17.356
    ],
    [
      "2024-09-27",
      17.374
    ],
    [
      "2024-09-30",
      17.168
    ],
    [
      "2024-10-01",
      17.226
    ],
    [
      "2024-10-03",
      16.808
    ],
    [
      "2024-10-04",
      16.607
    ],
    [
      "2024-10-07",
      16.296
    ],
    [
      "2024-10-08",
      16.623
    ],
    [
      "2024-10-09",
      16.802
    ],
    [
      "2024-10-10",
      16.758
    ],
    [
      "2024-10-11",
      16.721
    ],
    [
      "2024-10-14",
      16.712
    ],
    [
      "2024-10-15",
      16.703
    ],
    [
      "2024-10-16",
      16.621
    ],
    [
      "2024-10-17",
      16.143
    ],
    [
      "2024-10-18",
      16.141
    ],
    [
      "2024-10-21",
      16.154
    ],
    [
      "2024-10-22",
      15.757
    ],
    [
      "2024-10-23",
      15.821
    ],
    [
      "2024-10-24",
      15.663
    ],
    [
      "2024-10-25",
      15.381
    ],
    [
      "2024-10-28",
      15.305
    ],
    [
      "2024-10-29",
      15.235
    ],
    [
      "2024-10-30",
      15.368
    ],
    [
      "2024-10-31",
      15.347
    ],
    [
      "2024-11-04",
      15.335
    ],
    [
      "2024-11-05",
      15.341
    ],
    [
      "2024-11-06",
      15.593
    ],
    [
      "2024-11-07",
      15.448
    ],
    [
      "2024-11-08",
      15.341
    ],
    [
      "2024-11-11",
      15.348
    ],
    [
      "2024-11-12",
      15.114
    ],
    [
      "2024-11-13",
      14.732
    ],
    [
      "2024-11-14",
      14.91
    ],
    [
      "2024-11-18",
      14.891
    ],
    [
      "2024-11-19",
      15.095
    ],
    [
      "2024-11-21",
      14.955
    ],
    [
      "2024-11-22",
      15.104
    ],
    [
      "2024-11-25",
      15.259
    ],
    [
      "2024-11-26",
      15.293
    ],
    [
      "2024-11-27",
      15.484
    ],
    [
      "2024-11-28",
      15.422
    ],
    [
      "2024-11-29",
      15.457
    ],
    [
      "2024-12-02",
      15.563
    ],
    [
      "2024-12-03",
      15.644
    ],
    [
      "2024-12-04",
      15.631
    ],
    [
      "2024-12-05",
      15.717
    ],
    [
      "2024-12-06",
      15.838
    ],
    [
      "2024-12-09",
      15.796
    ],
    [
      "2024-12-10",
      15.843
    ],
    [
      "2024-12-11",
      15.867
    ],
    [
      "2024-12-12",
      15.717
    ],
    [
      "2024-12-13",
      15.749
    ],
    [
      "2024-12-16",
      15.807
    ],
    [
      "2024-12-17",
      15.644
    ],
    [
      "2024-12-18",
      15.554
    ],
    [
      "2024-12-19",
      15.481
    ],
    [
      "2024-12-20",
      15.197
    ],
    [
      "2024-12-23",
      15.124
    ],
    [
      "2024-12-24",
      15.211
    ],
    [
      "2024-12-26",
      15.244
    ],
    [
      "2024-12-27",
      15.324
    ],
    [
      "2024-12-30",
      15.172
    ],
    [
      "2024-12-31",
      15.214
    ],
    [
      "2025-01-01",
      15.357
    ],
    [
      "2025-01-02",
      15.701
    ],
    [
      "2025-01-03",
      15.595
    ],
    [
      "2025-01-06",
      15.206
    ],
    [
      "2025-01-07",
      15.185
    ],
    [
      "2025-01-08",
      15.122
    ],
    [
      "2025-01-09",
      15.048
    ],
    [
      "2025-01-10",
      14.848
    ],
    [
      "2025-01-13",
      14.395
    ],
    [
      "2025-01-14",
      14.633
    ],
    [
      "2025-01-15",
      14.712
    ],
    [
      "2025-01-16",
      14.817
    ],
    [
      "2025-01-17",
      14.803
    ],
    [
      "2025-01-20",
      14.76
    ],
    [
      "2025-01-21",
      14.478
    ],
    [
      "2025-01-22",
      14.424
    ],
    [
      "2025-01-23",
      14.556
    ],
    [
      "2025-01-24",
      14.396
    ],
    [
      "2025-01-27",
      14.144
    ],
    [
      "2025-01-28",
      14.162
    ],
    [
      "2025-01-29",
      14.34
    ],
    [
      "2025-01-30",
      14.407
    ],
    [
      "2025-01-31",
      14.658
    ],
    [
      "2025-02-03",
      14.947
    ],
    [
      "2025-02-04",
      14.985
    ],
    [
      "2025-02-05",
      15.01
    ],
    [
      "2025-02-06",
      14.918
    ],
    [
      "2025-02-07",
      14.963
    ],
    [
      "2025-02-10",
      14.736
    ],
    [
      "2025-02-11",
      14.379
    ],
    [
      "2025-02-12",
      14.224
    ],
    [
      "2025-02-13",
      14.214
    ],
    [
      "2025-02-14",
      13.975
    ],
    [
      "2025-02-17",
      14.016
    ],
    [
      "2025-02-18",
      13.952
    ],
    [
      "2025-02-19",
      14.125
    ],
    [
      "2025-02-20",
      14.248
    ],
    [
      "2025-02-21",
      14.125
    ],
    [
      "2025-02-24",
      14.019
    ],
    [
      "2025-02-25",
      14.035
    ],
    [
      "2025-02-27",
      13.822
    ],
    [
      "2025-02-28",
      13.517
    ],
    [
      "2025-03-03",
      13.478
    ],
    [
      "2025-03-04",
      13.435
    ],
    [
      "2025-03-05",
      13.709
    ],
    [
      "2025-03-06",
      13.862
    ],
    [
      "2025-03-07",
      13.817
    ],
    [
      "2025-03-10",
      13.602
    ],
    [
      "2025-03-11",
      13.547
    ],
    [
      "2025-03-12",
      13.571
    ],
    [
      "2025-03-13",
      13.447
    ],
    [
      "2025-03-17",
      13.46
    ],
    [
      "2025-03-18",
      13.8
    ],
    [
      "2025-03-19",
      13.988
    ],
    [
      "2025-03-20",
      14.116
    ],
    [
      "2025-03-21",
      14.274
    ],
    [
      "2025-03-24",
      14.428
    ],
    [
      "2025-03-25",
      14.237
    ],
    [
      "2025-03-26",
      14.141
    ],
    [
      "2025-03-27",
      14.167
    ],
    [
      "2025-03-28",
      14.033
    ],
    [
      "2025-03-31",
      14.032
    ],
    [
      "2025-04-01",
      13.968
    ],
    [
      "2025-04-02",
      14.093
    ],
    [
      "2025-04-03",
      13.995
    ],
    [
      "2025-04-04",
      13.702
    ],
    [
      "2025-04-07",
      13.291
    ],
    [
      "2025-04-08",
      13.497
    ],
    [
      "2025-04-09",
      13.46
    ],
    [
      "2025-04-11",
      13.703
    ],
    [
      "2025-04-15",
      14.077
    ],
    [
      "2025-04-16",
      14.106
    ],
    [
      "2025-04-17",
      14.26
    ],
    [
      "2025-04-21",
      14.519
    ],
    [
      "2025-04-22",
      14.583
    ],
    [
      "2025-04-23",
      14.715
    ],
    [
      "2025-04-24",
      14.654
    ],
    [
      "2025-04-25",
      14.347
    ],
    [
      "2025-04-28",
      14.438
    ],
    [
      "2025-04-29",
      14.456
    ],
    [
      "2025-04-30",
      14.499
    ],
    [
      "2025-05-02",
      14.526
    ],
    [
      "2025-05-05",
      14.718
    ],
    [
      "2025-05-06",
      14.645
    ],
    [
      "2025-05-07",
      14.816
    ],
    [
      "2025-05-08",
      14.626
    ],
    [
      "2025-05-09",
      14.524
    ],
    [
      "2025-05-12",
      15.077
    ],
    [
      "2025-05-13",
      15.1
    ],
    [
      "2025-05-14",
      15.294
    ],
    [
      "2025-05-15",
      15.476
    ],
    [
      "2025-05-16",
      15.595
    ],
    [
      "2025-05-19",
      15.732
    ],
    [
      "2025-05-20",
      15.441
    ],
    [
      "2025-05-21",
      15.608
    ],
    [
      "2025-05-22",
      15.514
    ],
    [
      "2025-05-23",
      15.619
    ],
    [
      "2025-05-26",
      15.629
    ],
    [
      "2025-05-27",
      15.591
    ],
    [
      "2025-05-28",
      15.476
    ],
    [
      "2025-05-29",
      15.482
    ],
    [
      "2025-05-30",
      15.445
    ],
    [
      "2025-06-02",
      15.523
    ],
    [
      "2025-06-03",
      15.449
    ],
    [
      "2025-06-04",
      15.535
    ],
    [
      "2025-06-05",
      15.61
    ],
    [
      "2025-06-06",
      15.725
    ],
    [
      "2025-06-09",
      15.864
    ],
    [
      "2025-06-10",
      15.827
    ],
    [
      "2025-06-11",
      15.847
    ],
    [
      "2025-06-12",
      15.605
    ],
    [
      "2025-06-13",
      15.504
    ],
    [
      "2025-06-16",
      15.597
    ],
    [
      "2025-06-17",
      15.522
    ],
    [
      "2025-06-18",
      15.597
    ],
    [
      "2025-06-19",
      15.54
    ],
    [
      "2025-06-20",
      15.71
    ],
    [
      "2025-06-23",
      15.625
    ],
    [
      "2025-06-24",
      15.786
    ],
    [
      "2025-06-25",
      16.009
    ],
    [
      "2025-06-27",
      16.137
    ],
    [
      "2025-06-30",
      16.252
    ],
    [
      "2025-07-01",
      16.401
    ],
    [
      "2025-07-02",
      16.52
    ],
    [
      "2025-07-03",
      16.527
    ],
    [
      "2025-07-04",
      16.555
    ],
    [
      "2025-07-07",
      16.55
    ],
    [
      "2025-07-08",
      16.563
    ],
    [
      "2025-07-09",
      16.704
    ],
    [
      "2025-07-10",
      16.719
    ],
    [
      "2025-07-11",
      16.628
    ],
    [
      "2025-07-14",
      16.772
    ],
    [
      "2025-07-15",
      16.899
    ],
    [
      "2025-07-16",
      16.871
    ],
    [
      "2025-07-17",
      16.904
    ],
    [
      "2025-07-18",
      16.82
    ],
    [
      "2025-07-21",
      16.838
    ],
    [
      "2025-07-22",
      16.825
    ],
    [
      "2025-07-23",
      16.927
    ],
    [
      "2025-07-24",
      16.886
    ],
    [
      "2025-07-25",
      16.686
    ],
    [
      "2025-07-28",
      16.574
    ],
    [
      "2025-07-29",
      16.778
    ],
    [
      "2025-07-30",
      16.807
    ],
    [
      "2025-07-31",
      16.816
    ],
    [
      "2025-08-01",
      16.685
    ],
    [
      "2025-08-04",
      16.89
    ],
    [
      "2025-08-05",
      16.879
    ],
    [
      "2025-08-06",
      16.691
    ],
    [
      "2025-08-07",
      16.701
    ],
    [
      "2025-08-08",
      16.57
    ],
    [
      "2025-08-11",
      16.646
    ],
    [
      "2025-08-12",
      16.755
    ],
    [
      "2025-08-13",
      16.877
    ],
    [
      "2025-08-14",
      16.851
    ],
    [
      "2025-08-18",
      17.485
    ],
    [
      "2025-08-19",
      17.813
    ],
    [
      "2025-08-20",
      17.856
    ],
    [
      "2025-08-21",
      17.756
    ],
    [
      "2025-08-22",
      17.651
    ],
    [
      "2025-08-25",
      17.705
    ],
    [
      "2025-08-26",
      17.699
    ],
    [
      "2025-08-28",
      17.647
    ],
    [
      "2025-08-29",
      17.631
    ],
    [
      "2025-09-01",
      18.069
    ],
    [
      "2025-09-02",
      18.231
    ],
    [
      "2025-09-03",
      18.323
    ],
    [
      "2025-09-04",
      18.23
    ],
    [
      "2025-09-05",
      18.381
    ],
    [
      "2025-09-08",
      18.696
    ],
    [
      "2025-09-09",
      18.72
    ],
    [
      "2025-09-10",
      18.602
    ],
    [
      "2025-09-11",
      18.508
    ],
    [
      "2025-09-12",
      18.517
    ],
    [
      "2025-09-15",
      18.56
    ],
    [
      "2025-09-16",
      18.792
    ],
    [
      "2025-09-17",
      18.852
    ],
    [
      "2025-09-18",
      18.888
    ],
    [
      "2025-09-19",
      18.965
    ],
    [
      "2025-09-22",
      18.914
    ],
    [
      "2025-09-23",
      18.965
    ],
    [
      "2025-09-24",
      18.87
    ],
    [
      "2025-09-25",
      18.74
    ],
    [
      "2025-09-26",
      18.487
    ],
    [
      "2025-09-29",
      18.329
    ],
    [
      "2025-09-30",
      18.343
    ],
    [
      "2025-10-01",
      18.453
    ],
    [
      "2025-10-03",
      18.553
    ],
    [
      "2025-10-06",
      18.542
    ],
    [
      "2025-10-07",
      18.624
    ],
    [
      "2025-10-08",
      18.534
    ],
    [
      "2025-10-09",
      18.509
    ],
    [
      "2025-10-10",
      18.583
    ],
    [
      "2025-10-13",
      18.534
    ],
    [
      "2025-10-14",
      18.509
    ],
    [
      "2025-10-15",
      18.626
    ],
    [
      "2025-10-16",
      18.744
    ],
    [
      "2025-10-17",
      18.732
    ],
    [
      "2025-10-20",
      18.861
    ],
    [
      "2025-10-23",
      18.779
    ],
    [
      "2025-10-24",
      18.635
    ],
    [
      "2025-10-27",
      18.743
    ],
    [
      "2025-10-28",
      18.808
    ],
    [
      "2025-10-29",
      18.799
    ],
    [
      "2025-10-30",
      18.76
    ],
    [
      "2025-10-31",
      18.77
    ],
    [
      "2025-11-03",
      18.826
    ],
    [
      "2025-11-04",
      18.753
    ],
    [
      "2025-11-06",
      18.517
    ],
    [
      "2025-11-07",
      18.555
    ],
    [
      "2025-11-10",
      18.611
    ],
    [
      "2025-11-11",
      18.684
    ],
    [
      "2025-11-12",
      18.79
    ],
    [
      "2025-11-13",
      18.702
    ],
    [
      "2025-11-14",
      18.548
    ],
    [
      "2025-11-17",
      18.608
    ],
    [
      "2025-11-18",
      18.507
    ],
    [
      "2025-11-19",
      18.738
    ],
    [
      "2025-11-20",
      18.714
    ],
    [
      "2025-11-21",
      18.609
    ],
    [
      "2025-11-24",
      18.654
    ],
    [
      "2025-11-25",
      18.606
    ],
    [
      "2025-11-26",
      18.769
    ],
    [
      "2025-11-27",
      18.64
    ],
    [
      "2025-11-28",
      18.681
    ],
    [
      "2025-12-01",
      18.788
    ],
    [
      "2025-12-02",
      18.821
    ],
    [
      "2025-12-03",
      18.696
    ],
    [
      "2025-12-04",
      18.655
    ],
    [
      "2025-12-05",
      18.627
    ],
    [
      "2025-12-08",
      18.364
    ],
    [
      "2025-12-09",
      18.393
    ],
    [
      "2025-12-10",
      18.307
    ],
    [
      "2025-12-11",
      18.485
    ],
    [
      "2025-12-12",
      18.514
    ],
    [
      "2025-12-15",
      18.457
    ],
    [
      "2025-12-16",
      18.327
    ],
    [
      "2025-12-17",
      18.263
    ],
    [
      "2025-12-18",
      18.31
    ],
    [
      "2025-12-19",
      18.499
    ],
    [
      "2025-12-22",
      18.572
    ],
    [
      "2025-12-23",
      18.627
    ],
    [
      "2025-12-24",
      18.584
    ],
    [
      "2025-12-26",
      18.483
    ],
    [
      "2025-12-29",
      18.361
    ],
    [
      "2025-12-30",
      18.408
    ],
    [
      "2025-12-31",
      18.545
    ],
    [
      "2026-01-01",
      18.693
    ],
    [
      "2026-01-02",
      18.955
    ],
    [
      "2026-01-05",
      19.078
    ],
    [
      "2026-01-06",
      19.005
    ],
    [
      "2026-01-07",
      18.961
    ],
    [
      "2026-01-08",
      18.777
    ],
    [
      "2026-01-09",
      18.506
    ],
    [
      "2026-01-12",
      18.479
    ],
    [
      "2026-01-13",
      18.539
    ],
    [
      "2026-01-14",
      18.465
    ],
    [
      "2026-01-16",
      18.286
    ],
    [
      "2026-01-19",
      18.242
    ],
    [
      "2026-01-20",
      17.848
    ],
    [
      "2026-01-21",
      17.805
    ],
    [
      "2026-01-22",
      17.968
    ],
    [
      "2026-01-23",
      17.681
    ],
    [
      "2026-01-27",
      17.65
    ],
    [
      "2026-01-28",
      17.778
    ],
    [
      "2026-01-29",
      17.636
    ],
    [
      "2026-01-30",
      17.844
    ],
    [
      "2026-02-02",
      17.77
    ],
    [
      "2026-02-03",
      18.33
    ],
    [
      "2026-02-04",
      18.588
    ],
    [
      "2026-02-05",
      18.442
    ],
    [
      "2026-02-06",
      18.405
    ],
    [
      "2026-02-09",
      18.504
    ],
    [
      "2026-02-10",
      18.716
    ],
    [
      "2026-02-11",
      19.038
    ],
    [
      "2026-02-12",
      18.975
    ],
    [
      "2026-02-13",
      18.748
    ],
    [
      "2026-02-16",
      18.571
    ],
    [
      "2026-02-17",
      18.669
    ],
    [
      "2026-02-18",
      18.71
    ],
    [
      "2026-02-19",
      18.405
    ],
    [
      "2026-02-20",
      18.488
    ],
    [
      "2026-02-23",
      18.664
    ],
    [
      "2026-02-24",
      18.533
    ],
    [
      "2026-02-25",
      18.838
    ],
    [
      "2026-02-26",
      18.856
    ],
    [
      "2026-02-27",
      18.604
    ],
    [
      "2026-03-02",
      18.144
    ],
    [
      "2026-03-04",
      17.642
    ],
    [
      "2026-03-05",
      17.902
    ],
    [
      "2026-03-06",
      17.737
    ],
    [
      "2026-03-09",
      17.175
    ],
    [
      "2026-03-10",
      17.571
    ],
    [
      "2026-03-11",
      17.264
    ],
    [
      "2026-03-12",
      16.971
    ],
    [
      "2026-03-13",
      16.485
    ],
    [
      "2026-03-16",
      16.571
    ],
    [
      "2026-03-17",
      16.783
    ],
    [
      "2026-03-18",
      17.081
    ],
    [
      "2026-03-19",
      16.487
    ],
    [
      "2026-03-20",
      16.59
    ],
    [
      "2026-03-23",
      16.009
    ],
    [
      "2026-03-24",
      16.343
    ],
    [
      "2026-03-25",
      16.696
    ],
    [
      "2026-03-27",
      16.28
    ],
    [
      "2026-03-30",
      15.885
    ],
    [
      "2026-03-31",
      15.885
    ],
    [
      "2026-04-01",
      16.278
    ],
    [
      "2026-04-02",
      16.249
    ],
    [
      "2026-04-06",
      16.394
    ],
    [
      "2026-04-07",
      16.44
    ],
    [
      "2026-04-08",
      17.292
    ],
    [
      "2026-04-09",
      17.267
    ],
    [
      "2026-04-10",
      17.677
    ],
    [
      "2026-04-13",
      17.305
    ],
    [
      "2026-04-15",
      17.646
    ],
    [
      "2026-04-16",
      17.732
    ],
    [
      "2026-04-17",
      17.89
    ],
    [
      "2026-04-20",
      17.845
    ],
    [
      "2026-04-21",
      17.919
    ],
    [
      "2026-04-22",
      17.908
    ],
    [
      "2026-04-23",
      17.584
    ],
    [
      "2026-04-24",
      17.319
    ],
    [
      "2026-04-27",
      17.64
    ],
    [
      "2026-04-28",
      17.534
    ],
    [
      "2026-04-29",
      17.64
    ],
    [
      "2026-04-30",
      17.575
    ],
    [
      "2026-05-04",
      17.687
    ],
    [
      "2026-05-05",
      17.695
    ],
    [
      "2026-05-06",
      17.955
    ],
    [
      "2026-05-07",
      18.184
    ],
    [
      "2026-05-08",
      18.182
    ],
    [
      "2026-05-11",
      17.928
    ],
    [
      "2026-05-12",
      17.533
    ],
    [
      "2026-05-13",
      17.458
    ],
    [
      "2026-05-14",
      17.514
    ],
    [
      "2026-05-15",
      17.435
    ],
    [
      "2026-05-18",
      17.184
    ],
    [
      "2026-05-19",
      17.295
    ],
    [
      "2026-05-20",
      17.304
    ],
    [
      "2026-05-21",
      17.323
    ],
    [
      "2026-05-22",
      17.399
    ],
    [
      "2026-05-25",
      17.721
    ],
    [
      "2026-05-26",
      17.699
    ],
    [
      "2026-05-27",
      17.88
    ],
    [
      "2026-05-29",
      17.61
    ],
    [
      "2026-06-01",
      17.387
    ],
    [
      "2026-06-02",
      17.491
    ],
    [
      "2026-06-03",
      17.526
    ],
    [
      "2026-06-04",
      17.569
    ],
    [
      "2026-06-05",
      17.511
    ],
    [
      "2026-06-08",
      17.24
    ],
    [
      "2026-06-09",
      17.568
    ],
    [
      "2026-06-10",
      17.422
    ],
    [
      "2026-06-11",
      17.341
    ],
    [
      "2026-06-12",
      17.846
    ],
    [
      "2026-06-15",
      18.404
    ],
    [
      "2026-06-16",
      18.387
    ],
    [
      "2026-06-17",
      18.369
    ],
    [
      "2026-06-18",
      18.439
    ],
    [
      "2026-06-19",
      18.506
    ],
    [
      "2026-06-22",
      18.722
    ],
    [
      "2026-06-23",
      18.586
    ],
    [
      "2026-06-24",
      18.586
    ],
    [
      "2026-06-25",
      18.725
    ],
    [
      "2026-06-29",
      18.575
    ],
    [
      "2026-06-30",
      18.659
    ],
    [
      "2026-07-01",
      18.871
    ],
    [
      "2026-07-02",
      19.14
    ],
    [
      "2026-07-03",
      19.18
    ],
    [
      "2026-07-06",
      19.316
    ]
  ]
}
