{"schemecode":"46320","amc":"Motilal Oswal Mutual Fund","amcSlug":"motilal-oswal","amcSchemeName":"Motilal Oswal Nifty 200 Momentum 30 Index Fund","amcSchemeCode":"YO32","sourceUrl":"https://www.motilaloswalmf.com/content/dam/motilal-mf/downloads/mf/month-end-portfolio/2026/may/Motilal%20Portfolio%2030%20April%202026%20-%20Final.xlsx","confidence":"exact","months":[{"key":"2026-06","label":"Jun 2026","coveragePct":99.85,"fetchedAt":"2026-07-17T13:17:39.862Z","allocation":[{"class":"Equity","pct":99.85}]},{"key":"2026-05","label":"May 2026","coveragePct":99.89,"fetchedAt":"2026-07-17T13:17:39.862Z","allocation":[{"class":"Equity","pct":99.89}]},{"key":"2026-04","label":"Apr 2026","coveragePct":99.94,"fetchedAt":"2026-07-17T13:17:39.862Z","allocation":[{"class":"Equity","pct":99.94}]},{"key":"2026-03","label":"Mar 2026","coveragePct":99.86,"fetchedAt":"2026-07-17T13:17:39.862Z","allocation":[{"class":"Equity","pct":99.86}]},{"key":"2026-02","label":"Feb 2026","coveragePct":100,"fetchedAt":"2026-07-17T13:17:39.862Z","allocation":[{"class":"Equity","pct":100}]},{"key":"2026-01","label":"Jan 2026","coveragePct":99.64,"fetchedAt":"2026-07-17T13:17:39.862Z","allocation":[{"class":"Equity","pct":99.64}]}],"rows":[{"name":"Shriram Finance Limited","isin":"INE721A01047","industry":"Finance","assetClass":"Equity","months":{"2026-01":{"pctToNav":5.36,"marketValueCr":49.93},"2026-02":{"pctToNav":5.51,"marketValueCr":53.7},"2026-03":{"pctToNav":5.15,"marketValueCr":43.29},"2026-04":{"pctToNav":4.98,"marketValueCr":47.21},"2026-05":{"pctToNav":4.98,"marketValueCr":47.81},"2026-06":{"pctToNav":5.08,"marketValueCr":49.31}}},{"name":"Cummins India Limited","isin":"INE298A01020","industry":"Industrial Products","assetClass":"Equity","months":{"2026-01":{"pctToNav":2.69,"marketValueCr":25.02},"2026-02":{"pctToNav":3.11,"marketValueCr":30.28},"2026-03":{"pctToNav":3.3,"marketValueCr":27.76},"2026-04":{"pctToNav":3.47,"marketValueCr":32.96},"2026-05":{"pctToNav":3.84,"marketValueCr":36.89},"2026-06":{"pctToNav":5.05,"marketValueCr":49.11}}},{"name":"Multi Commodity Exchange of India Limited","isin":"INE745G01043","industry":"Capital Markets","assetClass":"Equity","months":{"2026-06":{"pctToNav":4.96,"marketValueCr":48.16}}},{"name":"NTPC Limited","isin":"INE733E01010","industry":"Power","assetClass":"Equity","months":{"2026-06":{"pctToNav":4.96,"marketValueCr":48.16}}},{"name":"BSE Limited","isin":"INE118H01025","industry":"Capital Markets","assetClass":"Equity","months":{"2026-01":{"pctToNav":4.05,"marketValueCr":37.71},"2026-02":{"pctToNav":3.81,"marketValueCr":37.09},"2026-03":{"pctToNav":4.37,"marketValueCr":36.69},"2026-04":{"pctToNav":5.32,"marketValueCr":50.45},"2026-05":{"pctToNav":5.99,"marketValueCr":57.61},"2026-06":{"pctToNav":4.94,"marketValueCr":47.96}}},{"name":"Tata Steel Limited","isin":"INE081A01020","industry":"Ferrous Metals","assetClass":"Equity","months":{"2026-06":{"pctToNav":4.91,"marketValueCr":47.67}}},{"name":"Hindalco Industries Limited","isin":"INE038A01020","industry":"Non - Ferrous Metals","assetClass":"Equity","months":{"2026-01":{"pctToNav":5.57,"marketValueCr":51.84},"2026-02":{"pctToNav":5.19,"marketValueCr":50.6},"2026-03":{"pctToNav":5.75,"marketValueCr":48.3},"2026-04":{"pctToNav":6.06,"marketValueCr":57.51},"2026-05":{"pctToNav":6.51,"marketValueCr":62.57},"2026-06":{"pctToNav":4.86,"marketValueCr":47.23}}},{"name":"GE Vernova T&D India Limited","isin":"INE200A01026","industry":"Electrical Equipment","assetClass":"Equity","months":{"2026-06":{"pctToNav":4.86,"marketValueCr":47.18}}},{"name":"Adani Power Limited","isin":"INE814H01029","industry":"Power","assetClass":"Equity","months":{"2026-06":{"pctToNav":4.83,"marketValueCr":46.96}}},{"name":"Laurus Labs Limited","isin":"INE947Q01028","industry":"Pharmaceuticals & Biotechnology","assetClass":"Equity","months":{"2026-06":{"pctToNav":4.78,"marketValueCr":46.47}}},{"name":"Vedanta Limited","isin":"INE205A01025","industry":"Diversified Metals","assetClass":"Equity","months":{"2026-06":{"pctToNav":4.4,"marketValueCr":42.75}}},{"name":"The Federal Bank  Limited","isin":"INE171A01029","industry":"Banks","assetClass":"Equity","months":{"2026-01":{"pctToNav":3.24,"marketValueCr":30.12},"2026-02":{"pctToNav":3.27,"marketValueCr":31.9},"2026-03":{"pctToNav":3.28,"marketValueCr":27.53},"2026-04":{"pctToNav":3.26,"marketValueCr":30.9},"2026-05":{"pctToNav":3.25,"marketValueCr":31.19},"2026-06":{"pctToNav":3.71,"marketValueCr":36.09}}},{"name":"Bharat Heavy Electricals Limited","isin":"INE257A01026","industry":"Electrical Equipment","assetClass":"Equity","months":{"2026-06":{"pctToNav":3.46,"marketValueCr":33.64}}},{"name":"Bharat Forge Limited","isin":"INE465A01025","industry":"Auto Components","assetClass":"Equity","months":{"2026-06":{"pctToNav":3.39,"marketValueCr":32.97}}},{"name":"CG Power and Industrial Solutions Limited","isin":"INE067A01029","industry":"Electrical Equipment","assetClass":"Equity","months":{"2026-06":{"pctToNav":3.23,"marketValueCr":31.35}}},{"name":"Hitachi Energy India Limited","isin":"INE07Y701011","industry":"Electrical Equipment","assetClass":"Equity","months":{"2026-06":{"pctToNav":3.16,"marketValueCr":30.66}}},{"name":"Adani Energy Solutions Limited","isin":"INE931S01010","industry":"Power","assetClass":"Equity","months":{"2026-06":{"pctToNav":3.02,"marketValueCr":29.35}}},{"name":"Polycab India Limited","isin":"INE455K01017","industry":"Industrial Products","assetClass":"Equity","months":{"2026-06":{"pctToNav":2.93,"marketValueCr":28.5}}},{"name":"Samvardhana Motherson International Limited","isin":"INE775A01035","industry":"Auto Components","assetClass":"Equity","months":{"2026-06":{"pctToNav":2.89,"marketValueCr":28.1}}},{"name":"Torrent Pharmaceuticals Limited","isin":"INE685A01028","industry":"Pharmaceuticals & Biotechnology","assetClass":"Equity","months":{"2026-06":{"pctToNav":2.61,"marketValueCr":25.4}}},{"name":"National Aluminium Company Limited","isin":"INE139A01034","industry":"Non - Ferrous Metals","assetClass":"Equity","months":{"2026-06":{"pctToNav":2.52,"marketValueCr":24.49}}},{"name":"Adani Green Energy Limited","isin":"INE364U01010","industry":"Power","assetClass":"Equity","months":{"2026-06":{"pctToNav":2.31,"marketValueCr":22.41}}},{"name":"Vodafone Idea Limited","isin":"INE669E01016","industry":"Telecom - Services","assetClass":"Equity","months":{"2026-06":{"pctToNav":2.15,"marketValueCr":20.92}}},{"name":"Solar Industries India Limited","isin":"INE343H01029","industry":"Chemicals & Petrochemicals","assetClass":"Equity","months":{"2026-06":{"pctToNav":1.95,"marketValueCr":18.99}}},{"name":"ABB India Limited","isin":"INE117A01022","industry":"Electrical Equipment","assetClass":"Equity","months":{"2026-06":{"pctToNav":1.83,"marketValueCr":17.78}}},{"name":"KEI Industries Limited","isin":"INE878B01027","industry":"Industrial Products","assetClass":"Equity","months":{"2026-06":{"pctToNav":1.65,"marketValueCr":15.99}}},{"name":"Glenmark Pharmaceuticals Limited","isin":"INE935A01035","industry":"Pharmaceuticals & Biotechnology","assetClass":"Equity","months":{"2026-01":{"pctToNav":1.3,"marketValueCr":12.09},"2026-02":{"pctToNav":1.34,"marketValueCr":13.01},"2026-03":{"pctToNav":1.54,"marketValueCr":12.96},"2026-04":{"pctToNav":1.56,"marketValueCr":14.84},"2026-05":{"pctToNav":1.46,"marketValueCr":14.06},"2026-06":{"pctToNav":1.58,"marketValueCr":15.32}}},{"name":"Steel Authority of India Limited","isin":"INE114A01011","industry":"Ferrous Metals","assetClass":"Equity","months":{"2026-06":{"pctToNav":1.53,"marketValueCr":14.9}}},{"name":"Aditya Birla Capital Limited","isin":"INE674K01013","industry":"Finance","assetClass":"Equity","months":{"2026-01":{"pctToNav":2.03,"marketValueCr":18.94},"2026-02":{"pctToNav":2,"marketValueCr":19.51},"2026-03":{"pctToNav":1.97,"marketValueCr":16.51},"2026-04":{"pctToNav":2.09,"marketValueCr":19.81},"2026-05":{"pctToNav":2.17,"marketValueCr":20.88},"2026-06":{"pctToNav":1.32,"marketValueCr":12.8}}},{"name":"L&T Finance Limited","isin":"INE498L01015","industry":"Finance","assetClass":"Equity","months":{"2026-01":{"pctToNav":2.48,"marketValueCr":23.05},"2026-02":{"pctToNav":2.38,"marketValueCr":23.23},"2026-03":{"pctToNav":2.33,"marketValueCr":19.61},"2026-04":{"pctToNav":2.44,"marketValueCr":23.17},"2026-05":{"pctToNav":2.48,"marketValueCr":23.79},"2026-06":{"pctToNav":0.98,"marketValueCr":9.56}}},{"name":"State Bank of India","isin":"INE062A01020","industry":"Banks","assetClass":"Equity","months":{"2026-01":{"pctToNav":5.63,"marketValueCr":52.4},"2026-02":{"pctToNav":6.1,"marketValueCr":59.4},"2026-03":{"pctToNav":5.75,"marketValueCr":48.31},"2026-04":{"pctToNav":5.64,"marketValueCr":53.47},"2026-05":{"pctToNav":5.03,"marketValueCr":48.38}}},{"name":"Eicher Motors Limited","isin":"INE066A01021","industry":"Automobiles","assetClass":"Equity","months":{"2026-01":{"pctToNav":4.91,"marketValueCr":45.71},"2026-02":{"pctToNav":5.36,"marketValueCr":52.24},"2026-03":{"pctToNav":5.1,"marketValueCr":42.86},"2026-04":{"pctToNav":4.95,"marketValueCr":46.94},"2026-05":{"pctToNav":4.94,"marketValueCr":47.5}}},{"name":"Asian Paints Limited","isin":"INE021A01026","industry":"Consumer Durables","assetClass":"Equity","months":{"2026-01":{"pctToNav":4.47,"marketValueCr":41.56},"2026-02":{"pctToNav":4.24,"marketValueCr":41.32},"2026-03":{"pctToNav":4.47,"marketValueCr":37.57},"2026-04":{"pctToNav":4.54,"marketValueCr":43.04},"2026-05":{"pctToNav":4.91,"marketValueCr":47.15}}},{"name":"Bajaj Finance Ltd","isin":"INE296A01032","industry":"Finance","assetClass":"Equity","months":{"2026-01":{"pctToNav":4.7,"marketValueCr":43.71},"2026-02":{"pctToNav":4.88,"marketValueCr":47.57},"2026-03":{"pctToNav":4.55,"marketValueCr":38.21},"2026-04":{"pctToNav":4.78,"marketValueCr":45.31},"2026-05":{"pctToNav":4.58,"marketValueCr":44.03}}},{"name":"Bharti Airtel Limited","isin":"INE397D01024","industry":"Telecom - Services","assetClass":"Equity","months":{"2026-01":{"pctToNav":4.72,"marketValueCr":43.96},"2026-02":{"pctToNav":4.38,"marketValueCr":42.64},"2026-03":{"pctToNav":4.8,"marketValueCr":40.35},"2026-04":{"pctToNav":4.57,"marketValueCr":43.34},"2026-05":{"pctToNav":4.38,"marketValueCr":42.11}}},{"name":"TVS Motor Company Limited","isin":"INE494B01023","industry":"Automobiles","assetClass":"Equity","months":{"2026-01":{"pctToNav":4.48,"marketValueCr":41.68},"2026-02":{"pctToNav":4.57,"marketValueCr":44.57},"2026-03":{"pctToNav":4.6,"marketValueCr":38.66},"2026-04":{"pctToNav":4.29,"marketValueCr":40.73},"2026-05":{"pctToNav":4.08,"marketValueCr":39.22}}},{"name":"Maruti Suzuki India Limited","isin":"INE585B01010","industry":"Automobiles","assetClass":"Equity","months":{"2026-01":{"pctToNav":4.44,"marketValueCr":41.35},"2026-02":{"pctToNav":4.39,"marketValueCr":42.76},"2026-03":{"pctToNav":4.21,"marketValueCr":35.34},"2026-04":{"pctToNav":4.09,"marketValueCr":38.79},"2026-05":{"pctToNav":3.99,"marketValueCr":38.34}}},{"name":"Hero MotoCorp Limited","isin":"INE158A01026","industry":"Automobiles","assetClass":"Equity","months":{"2026-01":{"pctToNav":4.12,"marketValueCr":38.37},"2026-02":{"pctToNav":4.13,"marketValueCr":40.23},"2026-03":{"pctToNav":4.24,"marketValueCr":35.6},"2026-04":{"pctToNav":3.83,"marketValueCr":36.37},"2026-05":{"pctToNav":3.65,"marketValueCr":35.06}}},{"name":"InterGlobe Aviation Limited","isin":"INE646L01027","industry":"Transport Services","assetClass":"Equity","months":{"2026-01":{"pctToNav":3.79,"marketValueCr":35.24},"2026-02":{"pctToNav":3.86,"marketValueCr":37.6},"2026-03":{"pctToNav":3.65,"marketValueCr":30.65},"2026-04":{"pctToNav":3.57,"marketValueCr":33.87},"2026-05":{"pctToNav":3.62,"marketValueCr":34.82}}},{"name":"SBI Life Insurance Company Limited","isin":"INE123W01016","industry":"Insurance","assetClass":"Equity","months":{"2026-01":{"pctToNav":3.82,"marketValueCr":35.53},"2026-02":{"pctToNav":3.78,"marketValueCr":36.8},"2026-03":{"pctToNav":3.81,"marketValueCr":32.04},"2026-04":{"pctToNav":3.51,"marketValueCr":33.27},"2026-05":{"pctToNav":3.49,"marketValueCr":33.55}}},{"name":"AU Small Finance Bank Limited","isin":"INE949L01017","industry":"Banks","assetClass":"Equity","months":{"2026-01":{"pctToNav":3.27,"marketValueCr":30.43},"2026-02":{"pctToNav":3.1,"marketValueCr":30.16},"2026-03":{"pctToNav":3.15,"marketValueCr":26.47},"2026-04":{"pctToNav":3.41,"marketValueCr":32.37},"2026-05":{"pctToNav":3.27,"marketValueCr":31.45}}},{"name":"Muthoot Finance Limited","isin":"INE414G01012","industry":"Finance","assetClass":"Equity","months":{"2026-01":{"pctToNav":3.59,"marketValueCr":33.38},"2026-02":{"pctToNav":3.05,"marketValueCr":29.71},"2026-03":{"pctToNav":3.32,"marketValueCr":27.93},"2026-04":{"pctToNav":3.24,"marketValueCr":30.71},"2026-05":{"pctToNav":3.13,"marketValueCr":30.05}}},{"name":"Canara Bank","isin":"INE476A01022","industry":"Banks","assetClass":"Equity","months":{"2026-01":{"pctToNav":2.62,"marketValueCr":24.35},"2026-02":{"pctToNav":2.71,"marketValueCr":26.42},"2026-03":{"pctToNav":2.46,"marketValueCr":20.68},"2026-04":{"pctToNav":2.41,"marketValueCr":22.88},"2026-05":{"pctToNav":2.32,"marketValueCr":22.28}}},{"name":"One 97 Communications Limited","isin":"INE982J01020","industry":"Financial Technology (Fintech)","assetClass":"Equity","months":{"2026-01":{"pctToNav":2.27,"marketValueCr":21.09},"2026-02":{"pctToNav":2.12,"marketValueCr":20.7},"2026-03":{"pctToNav":2.15,"marketValueCr":18.03},"2026-04":{"pctToNav":2.2,"marketValueCr":20.9},"2026-05":{"pctToNav":2.23,"marketValueCr":21.39}}},{"name":"Fortis Healthcare Limited","isin":"INE061F01013","industry":"Healthcare Services","assetClass":"Equity","months":{"2026-01":{"pctToNav":2.01,"marketValueCr":18.7},"2026-02":{"pctToNav":2.16,"marketValueCr":21.04},"2026-03":{"pctToNav":2.11,"marketValueCr":17.71},"2026-04":{"pctToNav":2.2,"marketValueCr":20.86},"2026-05":{"pctToNav":2.19,"marketValueCr":21.03}}},{"name":"Max Financial Services Limited","isin":"INE180A01020","industry":"Insurance","assetClass":"Equity","months":{"2026-01":{"pctToNav":2.06,"marketValueCr":19.16},"2026-02":{"pctToNav":2.24,"marketValueCr":21.87},"2026-03":{"pctToNav":2.14,"marketValueCr":17.94},"2026-04":{"pctToNav":2.04,"marketValueCr":19.36},"2026-05":{"pctToNav":2.13,"marketValueCr":20.49}}},{"name":"Cholamandalam Investment and Finance Company Limited","isin":"INE121A01024","industry":"Finance","assetClass":"Equity","months":{"2026-01":{"pctToNav":2.24,"marketValueCr":20.84},"2026-02":{"pctToNav":2.3,"marketValueCr":22.46},"2026-03":{"pctToNav":2.09,"marketValueCr":17.54},"2026-04":{"pctToNav":2.16,"marketValueCr":20.53},"2026-05":{"pctToNav":2.11,"marketValueCr":20.25}}},{"name":"Ashok Leyland Limited","isin":"INE208A01029","industry":"Agricultural, Commercial & Construction Vehicles","assetClass":"Equity","months":{"2026-01":{"pctToNav":2.66,"marketValueCr":24.76},"2026-02":{"pctToNav":2.77,"marketValueCr":27},"2026-03":{"pctToNav":2.34,"marketValueCr":19.67},"2026-04":{"pctToNav":2.21,"marketValueCr":20.99},"2026-05":{"pctToNav":2.1,"marketValueCr":20.18}}},{"name":"FSN E-Commerce Ventures Limited","isin":"INE388Y01029","industry":"Retailing","assetClass":"Equity","months":{"2026-01":{"pctToNav":1.82,"marketValueCr":16.94},"2026-02":{"pctToNav":1.98,"marketValueCr":19.25},"2026-03":{"pctToNav":2.02,"marketValueCr":17},"2026-04":{"pctToNav":2.05,"marketValueCr":19.43},"2026-05":{"pctToNav":2.01,"marketValueCr":19.3}}},{"name":"Indian Bank","isin":"INE562A01011","industry":"Banks","assetClass":"Equity","months":{"2026-01":{"pctToNav":1.93,"marketValueCr":17.98},"2026-02":{"pctToNav":2.04,"marketValueCr":19.85},"2026-03":{"pctToNav":2.01,"marketValueCr":16.91},"2026-04":{"pctToNav":1.82,"marketValueCr":17.28},"2026-05":{"pctToNav":1.76,"marketValueCr":16.94}}},{"name":"GMR Airports Limited","isin":"INE776C01039","industry":"Transport Infrastructure","assetClass":"Equity","months":{"2026-01":{"pctToNav":1.58,"marketValueCr":14.75},"2026-02":{"pctToNav":1.65,"marketValueCr":16.07},"2026-03":{"pctToNav":1.61,"marketValueCr":13.5},"2026-04":{"pctToNav":1.64,"marketValueCr":15.59},"2026-05":{"pctToNav":1.69,"marketValueCr":16.26}}},{"name":"UPL Limited","isin":"INE628A01036","industry":"Fertilizers & Agrochemicals","assetClass":"Equity","months":{"2026-01":{"pctToNav":1.75,"marketValueCr":16.33},"2026-02":{"pctToNav":1.54,"marketValueCr":15.02},"2026-03":{"pctToNav":1.59,"marketValueCr":13.36},"2026-04":{"pctToNav":1.61,"marketValueCr":15.32},"2026-05":{"pctToNav":1.6,"marketValueCr":15.42}}},{"name":"TVS Motor Company Limited","isin":"INE494B04019","industry":"Automobiles","assetClass":"Equity","months":{"2026-01":{"pctToNav":0.04,"marketValueCr":0.38},"2026-02":{"pctToNav":0.04,"marketValueCr":0.38}}}]}
