{"schemecode":"d-motilal-oswal-106","amc":"Motilal Oswal Mutual Fund","amcSlug":"motilal-oswal","amcSchemeName":"MO Nifty MidSmall India Consumption Index Fund","amcSchemeCode":"","sourceUrl":"https://www.motilaloswalmf.com/content/dam/motilal-mf/downloads/mf/month-end-portfolio/2026/may/Motilal%20Portfolio%2030%20April%202026%20-%20Final.xlsx","confidence":"high","months":[{"key":"2026-03","label":"Mar 2026","coveragePct":100.03,"fetchedAt":"2026-07-17T13:17:39.862Z","allocation":[{"class":"Equity","pct":100.03}]},{"key":"2026-02","label":"Feb 2026","coveragePct":99.75,"fetchedAt":"2026-07-17T13:17:39.862Z","allocation":[{"class":"Equity","pct":99.75}]},{"key":"2026-01","label":"Jan 2026","coveragePct":100,"fetchedAt":"2026-07-17T13:17:39.862Z","allocation":[{"class":"Equity","pct":100}]}],"rows":[{"name":"Hero MotoCorp Limited","isin":"INE158A01026","industry":"Automobiles","assetClass":"Equity","months":{"2026-03":{"pctToNav":8.48,"marketValueCr":1.66},"2026-02":{"pctToNav":9,"marketValueCr":1.98},"2026-01":{"pctToNav":9.03,"marketValueCr":1.84}}},{"name":"Fortis Healthcare Limited","isin":"INE061F01013","industry":"Healthcare Services","assetClass":"Equity","months":{"2026-03":{"pctToNav":5.35,"marketValueCr":1.04},"2026-02":{"pctToNav":5.98,"marketValueCr":1.31},"2026-01":{"pctToNav":5.59,"marketValueCr":1.14}}},{"name":"Dixon Technologies (India) Limited","isin":"INE935N01020","industry":"Consumer Durables","assetClass":"Equity","months":{"2026-03":{"pctToNav":5.15,"marketValueCr":1.01},"2026-02":{"pctToNav":5.24,"marketValueCr":1.15},"2026-01":{"pctToNav":5.38,"marketValueCr":1.1}}},{"name":"Marico Limited","isin":"INE196A01026","industry":"Agricultural Food & other Products","assetClass":"Equity","months":{"2026-03":{"pctToNav":5.03,"marketValueCr":0.98},"2026-02":{"pctToNav":5.08,"marketValueCr":1.12},"2026-01":{"pctToNav":4.86,"marketValueCr":0.99}}},{"name":"Info Edge (India) Limited","isin":"INE663F01032","industry":"Retailing","assetClass":"Equity","months":{"2026-03":{"pctToNav":4.77,"marketValueCr":0.93}}},{"name":"Swiggy Limited","isin":"INE00H001014","industry":"Retailing","assetClass":"Equity","months":{"2026-03":{"pctToNav":4.61,"marketValueCr":0.9},"2026-02":{"pctToNav":4.91,"marketValueCr":1.08},"2026-01":{"pctToNav":5.21,"marketValueCr":1.06}}},{"name":"FSN E-Commerce Ventures Limited","isin":"INE388Y01029","industry":"Retailing","assetClass":"Equity","months":{"2026-03":{"pctToNav":4.15,"marketValueCr":0.81},"2026-02":{"pctToNav":4.42,"marketValueCr":0.97},"2026-01":{"pctToNav":4.09,"marketValueCr":0.83}}},{"name":"Alkem Laboratories Limited","isin":"INE540L01014","industry":"Pharmaceuticals & Biotechnology","assetClass":"Equity","months":{"2026-03":{"pctToNav":4,"marketValueCr":0.78},"2026-02":{"pctToNav":4,"marketValueCr":0.88},"2026-01":{"pctToNav":4.17,"marketValueCr":0.85}}},{"name":"Havells India Limited","isin":"INE176B01034","industry":"Consumer Durables","assetClass":"Equity","months":{"2026-03":{"pctToNav":3.88,"marketValueCr":0.76}}},{"name":"Voltas Limited","isin":"INE226A01021","industry":"Consumer Durables","assetClass":"Equity","months":{"2026-03":{"pctToNav":3.74,"marketValueCr":0.73},"2026-02":{"pctToNav":4.33,"marketValueCr":0.95},"2026-01":{"pctToNav":3.81,"marketValueCr":0.78}}},{"name":"The Phoenix Mills Limited","isin":"INE211B01039","industry":"Realty","assetClass":"Equity","months":{"2026-03":{"pctToNav":3.63,"marketValueCr":0.71},"2026-02":{"pctToNav":3.76,"marketValueCr":0.83},"2026-01":{"pctToNav":3.92,"marketValueCr":0.8}}},{"name":"Torrent Power Limited","isin":"INE813H01021","industry":"Power","assetClass":"Equity","months":{"2026-03":{"pctToNav":3.2,"marketValueCr":0.63},"2026-02":{"pctToNav":3.62,"marketValueCr":0.8},"2026-01":{"pctToNav":3.32,"marketValueCr":0.68}}},{"name":"Dabur India Limited","isin":"INE016A01026","industry":"Personal Products","assetClass":"Equity","months":{"2026-03":{"pctToNav":3.13,"marketValueCr":0.61},"2026-02":{"pctToNav":3.72,"marketValueCr":0.82},"2026-01":{"pctToNav":3.76,"marketValueCr":0.77}}},{"name":"Colgate Palmolive (India) Limited","isin":"INE259A01022","industry":"Personal Products","assetClass":"Equity","months":{"2026-03":{"pctToNav":3.04,"marketValueCr":0.59},"2026-02":{"pctToNav":3.61,"marketValueCr":0.79},"2026-01":{"pctToNav":3.5,"marketValueCr":0.71}}},{"name":"Vodafone Idea Limited","isin":"INE669E01016","industry":"Telecom - Services","assetClass":"Equity","months":{"2026-03":{"pctToNav":3.04,"marketValueCr":0.59},"2026-02":{"pctToNav":3.56,"marketValueCr":0.78},"2026-01":{"pctToNav":3.89,"marketValueCr":0.79}}},{"name":"Mankind Pharma Limited","isin":"INE634S01028","industry":"Pharmaceuticals & Biotechnology","assetClass":"Equity","months":{"2026-03":{"pctToNav":2.93,"marketValueCr":0.57},"2026-02":{"pctToNav":3.09,"marketValueCr":0.68},"2026-01":{"pctToNav":3.02,"marketValueCr":0.62}}},{"name":"Vishal Mega Mart Limited","isin":"INE01EA01019","industry":"Retailing","assetClass":"Equity","months":{"2026-03":{"pctToNav":2.89,"marketValueCr":0.57},"2026-02":{"pctToNav":3.05,"marketValueCr":0.67},"2026-01":{"pctToNav":3.38,"marketValueCr":0.69}}},{"name":"Godrej Properties Limited","isin":"INE484J01027","industry":"Realty","assetClass":"Equity","months":{"2026-03":{"pctToNav":2.83,"marketValueCr":0.55},"2026-02":{"pctToNav":3.14,"marketValueCr":0.69},"2026-01":{"pctToNav":2.96,"marketValueCr":0.6}}},{"name":"Blue Star Limited","isin":"INE472A01039","industry":"Consumer Durables","assetClass":"Equity","months":{"2026-03":{"pctToNav":2.7,"marketValueCr":0.53},"2026-02":{"pctToNav":3.06,"marketValueCr":0.67},"2026-01":{"pctToNav":2.96,"marketValueCr":0.6}}},{"name":"Radico Khaitan Limited","isin":"INE944F01028","industry":"Beverages","assetClass":"Equity","months":{"2026-03":{"pctToNav":2.66,"marketValueCr":0.52},"2026-02":{"pctToNav":2.52,"marketValueCr":0.55},"2026-01":{"pctToNav":2.78,"marketValueCr":0.57}}},{"name":"Page Industries Limited","isin":"INE761H01022","industry":"Textiles & Apparels","assetClass":"Equity","months":{"2026-03":{"pctToNav":2.59,"marketValueCr":0.51},"2026-02":{"pctToNav":2.29,"marketValueCr":0.5},"2026-01":{"pctToNav":2.52,"marketValueCr":0.51}}},{"name":"Prestige Estates Projects Limited","isin":"INE811K01011","industry":"Realty","assetClass":"Equity","months":{"2026-03":{"pctToNav":2.45,"marketValueCr":0.48},"2026-02":{"pctToNav":2.86,"marketValueCr":0.63},"2026-01":{"pctToNav":3.1,"marketValueCr":0.63}}},{"name":"Jubilant Foodworks Limited","isin":"INE797F01020","industry":"Leisure Services","assetClass":"Equity","months":{"2026-03":{"pctToNav":2.19,"marketValueCr":0.43},"2026-02":{"pctToNav":2.48,"marketValueCr":0.54},"2026-01":{"pctToNav":2.45,"marketValueCr":0.5}}},{"name":"Oberoi Realty Limited","isin":"INE093I01010","industry":"Realty","assetClass":"Equity","months":{"2026-03":{"pctToNav":2.16,"marketValueCr":0.42},"2026-02":{"pctToNav":2.18,"marketValueCr":0.48},"2026-01":{"pctToNav":2.21,"marketValueCr":0.45}}},{"name":"Patanjali Foods Limited","isin":"INE619A01035","industry":"Agricultural Food & other Products","assetClass":"Equity","months":{"2026-03":{"pctToNav":2.05,"marketValueCr":0.4},"2026-02":{"pctToNav":2.1,"marketValueCr":0.46},"2026-01":{"pctToNav":2.14,"marketValueCr":0.44}}},{"name":"ITC Hotels Limited","isin":"INE379A01028","industry":"Leisure Services","assetClass":"Equity","months":{"2026-03":{"pctToNav":1.99,"marketValueCr":0.39}}},{"name":"Indian Railway Catering And Tourism Corporation Limited","isin":"INE335Y01020","industry":"Leisure Services","assetClass":"Equity","months":{"2026-03":{"pctToNav":1.93,"marketValueCr":0.38},"2026-02":{"pctToNav":2.09,"marketValueCr":0.46},"2026-01":{"pctToNav":2.37,"marketValueCr":0.48}}},{"name":"Kalyan Jewellers India Limited","isin":"INE303R01014","industry":"Consumer Durables","assetClass":"Equity","months":{"2026-03":{"pctToNav":1.87,"marketValueCr":0.37},"2026-02":{"pctToNav":1.92,"marketValueCr":0.42},"2026-01":{"pctToNav":1.75,"marketValueCr":0.36}}},{"name":"Crompton Greaves Consumer Electricals Limited","isin":"INE299U01018","industry":"Consumer Durables","assetClass":"Equity","months":{"2026-03":{"pctToNav":1.85,"marketValueCr":0.36},"2026-02":{"pctToNav":2.02,"marketValueCr":0.44},"2026-01":{"pctToNav":1.79,"marketValueCr":0.37}}},{"name":"Abbott India Limited","isin":"INE358A01014","industry":"Pharmaceuticals & Biotechnology","assetClass":"Equity","months":{"2026-03":{"pctToNav":1.74,"marketValueCr":0.34},"2026-02":{"pctToNav":1.56,"marketValueCr":0.34},"2026-01":{"pctToNav":1.74,"marketValueCr":0.36}}},{"name":"Berger Paints (I) Limited","isin":"INE463A01038","industry":"Consumer Durables","assetClass":"Equity","months":{"2026-02":{"pctToNav":1.58,"marketValueCr":0.35},"2026-01":{"pctToNav":1.66,"marketValueCr":0.34}}},{"name":"United Breweries Limited","isin":"INE686F01025","industry":"Beverages","assetClass":"Equity","months":{"2026-02":{"pctToNav":1.41,"marketValueCr":0.31},"2026-01":{"pctToNav":1.33,"marketValueCr":0.27}}},{"name":"Brigade Enterprises Limited","isin":"INE791I01019","industry":"Realty","assetClass":"Equity","months":{"2026-02":{"pctToNav":1.17,"marketValueCr":0.26},"2026-01":{"pctToNav":1.31,"marketValueCr":0.27}}}]}
